{
  "$schema": "../node_modules/@angular-devkit/schematics/collection-schema.json",
  "schematics": {
    "builder-add": {
      "description": "A blank schematic.",
      "factory": "./builder-add/builder-add.factory",
      "schema": "./builder-add/schema.json"
    },
    "prettier": {
      "description": "Install and configure prettier",
      "factory": "./builder-generate/prettier/prettier.factory#prettierFactory",
      "schema": "./builder-generate/prettier/schema.json",
      "aliases": [
        "p"
      ]
    },
    "git-hooks": {
      "description": "Install and configure prettier",
      "factory": "./builder-generate/git-hooks/git-hooks.factory#gitHooksFactory",
      "aliases": [
        "gh"
      ]
    },
    "empty-folder": {
      "description": "Create an empty folder",
      "factory": "./builder-generate/empty-folder/empty-folder.factory#emptyFolderFactory",
      "schema": "./builder-generate/empty-folder/schema.json",
      "aliases": [
        "ef"
      ]
    },
    "remove-folder-content": {
      "description": "Create an empty folder",
      "factory": "./builder-generate/remove-folder-content/remove-folder-content.factory#removeFolderContent",
      "schema": "./builder-generate/remove-folder-content/schema.json",
      "aliases": [
        "rfc"
      ]
    },
    "schematics-library-bundler": {
      "description": "Integrate a bundler to compile a schematic library",
      "factory": "./builder-generate/schematics-library-bundler/schematics-library-bundler.factory#schematicsLibraryBundler",
      "schema": "./builder-generate/schematics-library-bundler/schema.json",
      "aliases": [
        "slb"
      ]
    },
    "add-utils": {
      "description": "Add utilities files to the project",
      "factory": "./builder-generate/add-utils/add-utils.factory#addUtilsFactory",
      "aliases": [
        "au"
      ]
    }
  }
}